odoo/addons/stock_rule_reserve_max_quantity/README.rst
odoo/addons/stock_rule_reserve_max_quantity/__init__.py
odoo/addons/stock_rule_reserve_max_quantity/__manifest__.py
odoo/addons/stock_rule_reserve_max_quantity/i18n/es.po
odoo/addons/stock_rule_reserve_max_quantity/i18n/it.po
odoo/addons/stock_rule_reserve_max_quantity/i18n/stock_rule_reserve_max_quantity.pot
odoo/addons/stock_rule_reserve_max_quantity/models/__init__.py
odoo/addons/stock_rule_reserve_max_quantity/models/stock_move.py
odoo/addons/stock_rule_reserve_max_quantity/models/stock_rule.py
odoo/addons/stock_rule_reserve_max_quantity/readme/CONTEXT.md
odoo/addons/stock_rule_reserve_max_quantity/readme/CONTRIBUTORS.md
odoo/addons/stock_rule_reserve_max_quantity/readme/CREDITS.md
odoo/addons/stock_rule_reserve_max_quantity/readme/DESCRIPTION.md
odoo/addons/stock_rule_reserve_max_quantity/readme/ROADMAP.md
odoo/addons/stock_rule_reserve_max_quantity/readme/USAGE.md
odoo/addons/stock_rule_reserve_max_quantity/static/description/icon.png
odoo/addons/stock_rule_reserve_max_quantity/static/description/index.html
odoo/addons/stock_rule_reserve_max_quantity/tests/__init__.py
odoo/addons/stock_rule_reserve_max_quantity/tests/test_stock_rule_reservation.py
odoo/addons/stock_rule_reserve_max_quantity/views/stock_rule_views.xml
odoo_addon_stock_rule_reserve_max_quantity-18.0.1.0.1.dist-info/METADATA
odoo_addon_stock_rule_reserve_max_quantity-18.0.1.0.1.dist-info/WHEEL
odoo_addon_stock_rule_reserve_max_quantity-18.0.1.0.1.dist-info/top_level.txt
odoo_addon_stock_rule_reserve_max_quantity-18.0.1.0.1.dist-info/RECORD
